calibration_scores/calculate_scores.py
calibration_scores-0.1.4.dist-info/METADATA
calibration_scores-0.1.4.dist-info/WHEEL
calibration_scores-0.1.4.dist-info/RECORD
